jsondbase/__init__.py
jsondbase/database.py
jsondbase-1.0.7.dist-info/LICENSE
jsondbase-1.0.7.dist-info/METADATA
jsondbase-1.0.7.dist-info/WHEEL
jsondbase-1.0.7.dist-info/top_level.txt
jsondbase-1.0.7.dist-info/RECORD
