Metadata-Version: 2.1
Name: jsondbase
Version: 1.0.7
Summary: like database with json file
Author: khiemndd
Classifier: Programming Language :: Python :: 3
Classifier: License :: OSI Approved :: MIT License
Classifier: Operating System :: OS Independent
Requires-Python: >=3.0
License-File: LICENSE
